odoo9_addon_web_widget_digitized_signature-9.0.1.0.0.99.dev7-py2.7-nspkg.pth
odoo9_addon_web_widget_digitized_signature-9.0.1.0.0.99.dev7.dist-info/METADATA
odoo9_addon_web_widget_digitized_signature-9.0.1.0.0.99.dev7.dist-info/RECORD
odoo9_addon_web_widget_digitized_signature-9.0.1.0.0.99.dev7.dist-info/WHEEL
odoo9_addon_web_widget_digitized_signature-9.0.1.0.0.99.dev7.dist-info/namespace_packages.txt
odoo9_addon_web_widget_digitized_signature-9.0.1.0.0.99.dev7.dist-info/top_level.txt
odoo_addons/web_widget_digitized_signature/README.rst
odoo_addons/web_widget_digitized_signature/__init__.py
odoo_addons/web_widget_digitized_signature/__openerp__.py
odoo_addons/web_widget_digitized_signature/i18n/ca.po
odoo_addons/web_widget_digitized_signature/i18n/de.po
odoo_addons/web_widget_digitized_signature/i18n/es.po
odoo_addons/web_widget_digitized_signature/i18n/fr.po
odoo_addons/web_widget_digitized_signature/i18n/pt_BR.po
odoo_addons/web_widget_digitized_signature/i18n/sl.po
odoo_addons/web_widget_digitized_signature/models/__init__.py
odoo_addons/web_widget_digitized_signature/models/mail_thread.py
odoo_addons/web_widget_digitized_signature/models/res_users.py
odoo_addons/web_widget_digitized_signature/static/description/icon.png
odoo_addons/web_widget_digitized_signature/static/lib/jSignature/jSignatureCustom.js
odoo_addons/web_widget_digitized_signature/static/src/js/digital_sign.js
odoo_addons/web_widget_digitized_signature/static/src/xml/digital_sign.xml
odoo_addons/web_widget_digitized_signature/tests/__init__.py
odoo_addons/web_widget_digitized_signature/tests/test_signature_tracking.py
odoo_addons/web_widget_digitized_signature/views/res_users_view.xml
odoo_addons/web_widget_digitized_signature/views/web_digital_sign_view.xml
