Metadata-Version: 2.1
Name: odoo9-addon-web-widget-digitized-signature
Version: 9.0.1.0.0.99.dev7
Summary: Web Widget Digitized Signature
Home-page: http://www.serpentcs.com
Author: Serpent Consulting Services Pvt. Ltd., Agile Business Group, Tecnativa, Odoo Community Association (OCA)
Author-email: support@odoo-community.org
License: AGPL-3
Platform: UNKNOWN
Classifier: Programming Language :: Python
Classifier: Framework :: Odoo
Classifier: License :: OSI Approved :: GNU Affero General Public License v3
Requires-Python: ~=2.7
Requires-Dist: odoo (<9.1a,>=9.0a)
